zenbase/__init__.py
zenbase/settings.py
zenbase/types.py
zenbase/utils.py
zenbase/adaptors/__init__.py
zenbase/adaptors/arize.py
zenbase/adaptors/braintrust.py
zenbase/adaptors/arize/__init__.py
zenbase/adaptors/arize/adaptor.py
zenbase/adaptors/arize/dataset_helper.py
zenbase/adaptors/arize/evaluation_helper.py
zenbase/adaptors/base/adaptor.py
zenbase/adaptors/base/dataset_helper.py
zenbase/adaptors/base/evaluation_helper.py
zenbase/adaptors/json/adaptor.py
zenbase/adaptors/json/dataset_helper.py
zenbase/adaptors/json/evaluation_helper.py
zenbase/adaptors/langchain/__init__.py
zenbase/adaptors/langchain/adaptor.py
zenbase/adaptors/langchain/dataset_helper.py
zenbase/adaptors/langchain/evaluation_helper.py
zenbase/adaptors/langfuse_helper/__init__.py
zenbase/adaptors/langfuse_helper/adaptor.py
zenbase/adaptors/langfuse_helper/dataset_helper.py
zenbase/adaptors/langfuse_helper/evaluation_helper.py
zenbase/adaptors/lunary/__init__.py
zenbase/adaptors/lunary/adaptor.py
zenbase/adaptors/lunary/dataset_helper.py
zenbase/adaptors/lunary/evaluation_helper.py
zenbase/adaptors/parea/__init__.py
zenbase/adaptors/parea/adaptor.py
zenbase/adaptors/parea/dataset_helper.py
zenbase/adaptors/parea/evaluation_helper.py
zenbase/core/managers.py
zenbase/optim/base.py
zenbase/optim/metric/bootstrap_few_shot.py
zenbase/optim/metric/labeled_few_shot.py
zenbase/optim/metric/types.py
zenbase/predefined/__init__.py
zenbase/predefined/base/function_generator.py
zenbase/predefined/base/optimizer.py
zenbase/predefined/generic_lm_function/optimizer.py
zenbase/predefined/single_class_classifier/__init__.py
zenbase/predefined/single_class_classifier/classifier.py
zenbase/predefined/single_class_classifier/function_generator.py
zenbase/predefined/syntethic_data/single_class_classifier.py
zenbase-0.0.22.dist-info/METADATA
zenbase-0.0.22.dist-info/WHEEL
zenbase-0.0.22.dist-info/RECORD
