Metadata-Version: 2.3
Name: zenbase
Version: 0.0.22
Summary: LLMs made Zen
Author-email: Cyrus Nouroozi <cyrus@zenbase.ai>
Requires-Python: >=3.10
Requires-Dist: anyio>=4.4.0
Requires-Dist: cloudpickle>=3.0.0
Requires-Dist: faker>=24.2.0
Requires-Dist: instructor>=1.3.5
Requires-Dist: opentelemetry-api>=1.25.0
Requires-Dist: opentelemetry-sdk>=1.25.0
Requires-Dist: pksuid>=1.1.2
Requires-Dist: posthog>=3.5.0
Requires-Dist: pyee>=11.1.0
Requires-Dist: structlog>=24.2.0
